setup.py
sqlnet/__init__.py
sqlnet/connection.py
sqlnet/cursor.py
sqlnet/sqlnet.py
sqlnet/sqlnet_exceptions.py
sqlnet.egg-info/PKG-INFO
sqlnet.egg-info/SOURCES.txt
sqlnet.egg-info/dependency_links.txt
sqlnet.egg-info/not-zip-safe
sqlnet.egg-info/top_level.txt