Metadata-Version: 1.0
Name: sqlnet
Version: 0.0.1dev
Summary: A DB API v2.0 compatible wrapper to .NET SqlClient
Home-page: https://github.com/beckettsimmons/sqlnet
Author: Beckett Simmons
Author-email: beckettsimmons@hotmail.com
License: MIT
Platform: UNKNOWN
